itinerizer/__init__.py
itinerizer/__version__.py
itinerizer/cli.py
itinerizer/config.py
itinerizer/constants.py
itinerizer/manager.py
itinerizer/models.py
itinerizer/py.typed
itinerizer/storage.py
itinerizer/validation.py
itinerizer/server/__init__.py
itinerizer/server/app.py
itinerizer/server/cli.py
itinerizer-0.5.6.dist-info/licenses/AUTHORS
itinerizer-0.5.6.dist-info/licenses/LICENSE
itinerizer-0.5.6.dist-info/METADATA
itinerizer-0.5.6.dist-info/WHEEL
itinerizer-0.5.6.dist-info/entry_points.txt
itinerizer-0.5.6.dist-info/top_level.txt
itinerizer-0.5.6.dist-info/RECORD
