Metadata-Version: 2.4
Name: itinerizer
Version: 0.5.6
Summary: A comprehensive travel itinerary management system with JSON storage
Author-email: Itinerizer Contributors <contact@itinerizer.io>
Maintainer-email: Itinerizer Contributors <contact@itinerizer.io>
License: MIT
Project-URL: Homepage, https://github.com/bobmatnyc/itinerizer
Project-URL: Documentation, https://itinerizer.readthedocs.io
Project-URL: Repository, https://github.com/bobmatnyc/itinerizer.git
Project-URL: Bug Tracker, https://github.com/bobmatnyc/itinerizer/issues
Project-URL: Changelog, https://github.com/bobmatnyc/itinerizer/blob/main/CHANGELOG.md
Keywords: travel,itinerary,trip,planning,booking,tourism,vacation,business-travel,json-storage
Classifier: Development Status :: 4 - Beta
Classifier: Intended Audience :: Developers
Classifier: License :: OSI Approved :: MIT License
Classifier: Operating System :: OS Independent
Classifier: Programming Language :: Python
Classifier: Programming Language :: Python :: 3
Classifier: Programming Language :: Python :: 3.8
Classifier: Programming Language :: Python :: 3.9
Classifier: Programming Language :: Python :: 3.10
Classifier: Programming Language :: Python :: 3.11
Classifier: Programming Language :: Python :: 3.12
Classifier: Topic :: Software Development :: Libraries :: Python Modules
Classifier: Topic :: Office/Business
Classifier: Topic :: Other/Nonlisted Topic
Requires-Python: >=3.8
License-File: LICENSE
License-File: AUTHORS
Requires-Dist: pydantic>=2.0.0
Requires-Dist: python-dateutil>=2.8.2
Provides-Extra: server
Requires-Dist: fastapi>=0.100.0; extra == "server"
Requires-Dist: uvicorn[standard]>=0.23.0; extra == "server"
Requires-Dist: python-multipart>=0.0.6; extra == "server"
Provides-Extra: web
Requires-Dist: flask>=3.0.0; extra == "web"
Requires-Dist: flask-cors>=4.0.0; extra == "web"
Requires-Dist: flask-session>=0.5.0; extra == "web"
Requires-Dist: requests>=2.31.0; extra == "web"
Provides-Extra: nlp
Requires-Dist: openai>=1.0.0; extra == "nlp"
Requires-Dist: tiktoken>=0.5.0; extra == "nlp"
Provides-Extra: performance
Requires-Dist: orjson>=3.9.0; extra == "performance"
Provides-Extra: dev
Requires-Dist: pytest>=7.4.0; extra == "dev"
Requires-Dist: pytest-cov>=4.1.0; extra == "dev"
Requires-Dist: pytest-asyncio>=0.21.0; extra == "dev"
Requires-Dist: black>=23.0.0; extra == "dev"
Requires-Dist: flake8>=6.0.0; extra == "dev"
Requires-Dist: mypy>=1.4.0; extra == "dev"
Requires-Dist: pre-commit>=3.3.0; extra == "dev"
Provides-Extra: all
Requires-Dist: itinerizer[dev,nlp,performance,server,web]; extra == "all"
Dynamic: license-file
